openai_mcp_server/__init__.py
openai_mcp_server/server.py
openai_mcp_server-1.0.0.dist-info/METADATA
openai_mcp_server-1.0.0.dist-info/WHEEL
openai_mcp_server-1.0.0.dist-info/entry_points.txt
openai_mcp_server-1.0.0.dist-info/RECORD
