Metadata-Version: 2.4
Name: openai-mcp-server
Version: 1.0.0
Summary: Dockerized MCP server for OpenAI models
Requires-Python: >=3.13
Requires-Dist: mcp>=1.6.0
